cacheMeOutside/__init__.py
cacheMeOutside/cacheMeOutside.py
CacheMeOutside-1.0.0.dist-info/METADATA
CacheMeOutside-1.0.0.dist-info/WHEEL
CacheMeOutside-1.0.0.dist-info/top_level.txt
CacheMeOutside-1.0.0.dist-info/RECORD
